zulip_exporter/InfoCollector.py
zulip_exporter/SubscriptionCollector.py
zulip_exporter/UserCollector.py
zulip_exporter/ZulipExporter.py
zulip_exporter/__init__.py
zulip_exporter-0.0.9.dist-info/METADATA
zulip_exporter-0.0.9.dist-info/WHEEL
zulip_exporter-0.0.9.dist-info/entry_points.txt
zulip_exporter-0.0.9.dist-info/RECORD
