Metadata-Version: 2.1
Name: zulip-exporter
Version: 0.0.9
Summary: A Zulip exporter for Prometheus
License: MIT
Author: Mikke Schirén
Author-email: mikke.schiren@digitalist.com
Requires-Python: >=3.12,<4.0
Classifier: License :: OSI Approved :: MIT License
Classifier: Programming Language :: Python :: 3
Classifier: Programming Language :: Python :: 3.12
Requires-Dist: prometheus-client (>=0.21.0,<0.22.0)
Requires-Dist: zulip (>=0.9.0,<0.10.0)
